mpopt_lulav/__init__.py
mpopt_lulav/mpopt_lulav.py
mpopt_lulav-0.6.dist-info/LICENSE.txt
mpopt_lulav-0.6.dist-info/METADATA
mpopt_lulav-0.6.dist-info/WHEEL
mpopt_lulav-0.6.dist-info/top_level.txt
mpopt_lulav-0.6.dist-info/RECORD
